gbizinfo_lod/__init__.py
gbizinfo_lod/client.py
gbizinfo_lod/command.py
gbizinfo_lod/mappers/__init__.py
gbizinfo_lod/mappers/_katsudo.py
gbizinfo_lod/mappers/chotatsu.py
gbizinfo_lod/mappers/hojin.py
gbizinfo_lod/mappers/hojyokin.py
gbizinfo_lod/mappers/hyosho.py
gbizinfo_lod/mappers/shokuba.py
gbizinfo_lod/mappers/todokede.py
gbizinfo_lod/mappers/tokkyo.py
gbizinfo_lod/mappers/zaimu.py
gbizinfo_lod/namespace.py
gbizinfo_lod-0.2.2.dist-info/LICENSE
gbizinfo_lod-0.2.2.dist-info/METADATA
gbizinfo_lod-0.2.2.dist-info/WHEEL
gbizinfo_lod-0.2.2.dist-info/entry_points.txt
gbizinfo_lod-0.2.2.dist-info/RECORD
