Metadata-Version: 2.1
Name: gbizinfo-lod
Version: 0.2.2
Summary: A tool to generate LOD datasets for gBizINFO
Home-page: https://github.com/Babibubebon/gbizinfo-lod
License: MIT
Keywords: rdf,linked open data
Author: Babibubebon
Author-email: babibubebon@babibubebo.org
Requires-Python: >=3.12,<4.0
Classifier: License :: OSI Approved :: MIT License
Classifier: Programming Language :: Python :: 3
Classifier: Programming Language :: Python :: 3.12
Requires-Dist: click (>=8.1.7,<9.0.0)
Requires-Dist: isal (>=1.6.1,<2.0.0)
Requires-Dist: joblib (>=1.4.2,<2.0.0)
Requires-Dist: rdflib (>=7.0.0,<8.0.0)
Requires-Dist: requests (>=2.32.2,<3.0.0)
Project-URL: Repository, https://github.com/Babibubebon/gbizinfo-lod
